simboba/__init__.py
simboba/boba.py
simboba/cli.py
simboba/config.py
simboba/judge.py
simboba/schemas.py
simboba/server.py
simboba/storage.py
simboba/prompts/__init__.py
simboba/prompts/generation.py
simboba/prompts/judge.py
simboba/samples/setup.py
simboba/samples/test.py
simboba/static/favicon.svg
simboba/static/index.html
simboba/static/vite.svg
simboba/static/assets/index-D1APp0AH.js
simboba/static/assets/index-Di3xt5W5.css
simboba/utils/__init__.py
simboba/utils/llm.py
simboba-0.1.7.dist-info/METADATA
simboba-0.1.7.dist-info/WHEEL
simboba-0.1.7.dist-info/entry_points.txt
simboba-0.1.7.dist-info/RECORD
