Metadata-Version: 2.4
Name: simboba
Version: 0.1.7
Summary: A lightweight tool for generating annotated eval datasets and running LLM-as-judge evaluations
Project-URL: Homepage, https://github.com/ntkris/simboba
Project-URL: Repository, https://github.com/ntkris/simboba
Project-URL: Issues, https://github.com/ntkris/simboba/issues
Author-email: Krishna Nandakumar <krishna@getaide.ai>
License-Expression: MIT
Keywords: ai,eval,evaluation,judge,llm,testing
Classifier: Development Status :: 4 - Beta
Classifier: Environment :: Console
Classifier: Environment :: Web Environment
Classifier: Intended Audience :: Developers
Classifier: License :: OSI Approved :: MIT License
Classifier: Programming Language :: Python :: 3
Classifier: Programming Language :: Python :: 3.9
Classifier: Programming Language :: Python :: 3.10
Classifier: Programming Language :: Python :: 3.11
Classifier: Programming Language :: Python :: 3.12
Classifier: Topic :: Software Development :: Testing
Requires-Python: >=3.9
Requires-Dist: click>=8.0.0
Requires-Dist: fastapi>=0.104.0
Requires-Dist: litellm>=1.0.0
Requires-Dist: pydantic>=2.0.0
Requires-Dist: pypdf>=3.0.0
Requires-Dist: python-dotenv>=1.0.0
Requires-Dist: python-multipart>=0.0.6
Requires-Dist: pyyaml>=6.0.0
Requires-Dist: uvicorn>=0.24.0
Provides-Extra: dev
Requires-Dist: httpx>=0.25.0; extra == 'dev'
Requires-Dist: pytest>=7.0.0; extra == 'dev'
